{"match":{"goalscorers":{"home":["J Daly (67)"],"away":["S Thompson (11)"]},"date":"Saturday 6th August 2011","home_team":"Dundee United","away_team":"St Mirren","ft_home_goals":"1","ft_away_goals":"1","ht_home_goals":"0","ht_away_goals":"1"},"extra_info":{"Official":"Crawford Allan","Attendance":"6,594","Venue":"Tannadice Park"},"stats":{"Goals":{"home":"1","away":"1"},"Assists":{"home":"1","away":"1"},"Shots":{"home":"25","away":"7"},"On Target":{"home":"10","away":"4"},"Off Target":{"home":"15","away":"3"},"Crosses":{"home":"30","away":"8"},"Corners":{"home":"7","away":"1"},"Throw Ins":{"home":"24","away":"19"},"Saves":{"home":"5","away":"5"},"Clearances":{"home":"4","away":"20"},"Goal Kicks":{"home":"6","away":"19"},"Blocks":{"home":"0","away":"9"},"Free Kicks":{"home":"10","away":"13"},"Offside":{"home":"4","away":"1"},"Yellow Cards":{"home":"1","away":"3"},"Red Cards":{"home":"0","away":"1"}},"squads":{"home":{"formation":"4-4-2","first_11":{"1":"Dusan Pernis","2":"Sean Dillon","3":"Paul Dixon","5":"Garry Kenneth","12":"Keith Watson","4":"Scott Severin","6":"William Flood","11":"John Rankin","20":"Scott Allan","9":"Jon Daly","15":"Johnny Russell"},"substitutes":{"13":"Steve Banks","14":"Barry Douglas","8":"Scott Robertson","16":"Stuart Armstrong","17":"Gary Mackay-Steven","22":"Ryan Dow","23":"Dale Hilson"}},"away":{"formation":"4-3-3","first_11":{"1":"Craig Samson","2":"David van Zanten","4":"Darren McGregor","5":"Lee Mair","22":"Jeroen Tesselaar","6":"Jim Goodwin","8":"Steven Thomson","21":"Gary Teale","9":"Steven Thompson","10":"Paul McGowan","11":"Nigel Hasselbaink"},"substitutes":{"25":"Adam McHugh","14":"Marc McAusland","20":"Dominic Kennedy","17":"Kenneth McLean","28":"Graham Carey","19":"Jon McShane","32":"Mark Lamont"}}},"incidents":{"substitutions":{"home":["4. Scott Severin (6+0' Serious Injury)","8. Scott Robertson (6+0' Serious Injury 64+0' Tactical)","17. Gary Mackay-Steven (64+0' Tactical)"],"away":["4. Darren McGregor (73+0' Injury)","21. Gary Teale (65+0' Tactical)","9. Steven Thompson (80+0' Tactical)","14. Marc McAusland (73+0' Injury)","17. Kenneth McLean (80+0' Tactical)","19. Jon McShane (65+0' Tactical)"]},"yellow cards":{"home":["3. Paul Dixon  (87+0', Unsporting behaviour)"],"away":["6. Jim Goodwin  (46+0', Dissent)","9. Steven Thompson  (45+6', Dissent)","10. Paul McGowan  (63+0', Unsporting behaviour)"]},"red cards":{"away":["11. Nigel Hasselbaink  (45+6', Serious Foul Play)"]}}}