{"match":{"goalscorers":{"home":[],"away":["S Naismith (21)","N Jelavic (74)"]},"date":"Sunday 23rd October 2011","home_team":"Hearts","away_team":"Rangers","ft_home_goals":"0","ft_away_goals":"2","ht_home_goals":"0","ht_away_goals":"1"},"extra_info":{"Official":"Calum Murray","Attendance":"15,495","Venue":"Tynecastle Stadium"},"stats":{"Goals":{"home":"0","away":"2"},"Assists":{"home":"0","away":"2"},"Shots":{"home":"16","away":"7"},"On Target":{"home":"12","away":"4"},"Off Target":{"home":"4","away":"3"},"Crosses":{"home":"10","away":"4"},"Corners":{"home":"6","away":"3"},"Throw Ins":{"home":"37","away":"25"},"Saves":{"home":"0","away":"4"},"Clearances":{"home":"3","away":"9"},"Goal Kicks":{"home":"6","away":"11"},"Blocks":{"home":"2","away":"7"},"Free Kicks":{"home":"19","away":"15"},"Offside":{"home":"2","away":"3"},"Hand Balls":{"home":"1","away":"2"},"Yellow Cards":{"home":"4","away":"2"}},"squads":{"home":{"formation":"4-5-1","first_11":[[25,"Marian Kello"],[3,"Danny Grainger"],[6,"Andy Webster"],[26,"Marius Zaliukas"],[2,"Jamie Hamill"],[4,"Eggert Jonsson"],[8,"Ian Black"],[12,"David Templeton"],[16,"Ryan Stevenson"],[19,"Rudi Skacel"],[31,"Adrian Mrowiec"]],"substitutes":[[30,"Jamie MacDonald"],[13,"David Obua"],[17,"Ryan McGowan"],[21,"Mehdi Taouil"],[18,"Arvydas Novikovas"],[22,"Gordon Smith"],[27,"Scott Robinson"]]},"away":{"formation":"4-1-4-1","first_11":[[1,"Allan McGregor"],[2,"Dorin Goian"],[5,"Sasa Papac"],[12,"Lee Wallace"],[16,"Steven Whittaker"],[18,"Carlos Bocanegra"],[6,"Lee McCulloch"],[7,"Maurice Edu"],[8,"Steven Davis"],[11,"Kyle Lafferty"],[14,"Steven Naismith"]],"substitutes":[[25,"Neil Alexander"],[4,"Kirk Broadfoot"],[27,"Gregg Wylde"],[32,"Ross Perry"],[21,"Alejandro Bedoya"],[9,"Nikica Jelavic"],[10,"John Fleck"]]}},"incidents":{"substitutions":{"home":["4. Eggert Jonsson (79+0' Tactical)","8. Ian Black (83+0' Tactical)","21. Mehdi Taouil (79+0' Tactical)","22. Gordon Smith (83+0' Tactical)"],"away":["5. Sasa Papac (72+0' Tactical)","16. Steven Whittaker (77+0' Tactical)","4. Kirk Broadfoot (77+0' Tactical)","27. Gregg Wylde (72+0' Tactical)"]},"yellow cards":{"home":["3. Danny Grainger  (31+0', Unsporting behaviour)","26. Marius Zaliukas  (90+0', Unsporting behaviour)","8. Ian Black  (83+0', Unsporting behaviour)","16. Ryan Stevenson  (45+0', Unsporting behaviour)"],"away":["2. Dorin Goian  (69+0', Unsporting behaviour)","16. Steven Whittaker  (11+0', Unsporting behaviour)"]},"red cards":[]}}