{"match":{"goalscorers":{"home":["R Anderson (51)"],"away":["H Larsson (30)"]},"date":"Thursday 2nd January 2003","home_team":"Aberdeen","away_team":"Celtic","ft_home_goals":"1","ft_away_goals":"1","ht_home_goals":"0","ht_away_goals":"1"},"extra_info":{"Attendance":"16,331","Venue":"Pittodrie Stadium"},"stats":{"Goals":{"home":"1","away":"1"},"Assists":{"home":"1","away":"0"},"Shots":{"home":"7","away":"8"},"On Target":{"home":"3","away":"4"},"Off Target":{"home":"4","away":"4"},"Corners":{"home":"10","away":"7"},"Fouls":{"home":"13","away":"15"}},"squads":{"home":{"formation":"3-5-2","first_11":{"30":"David Preece","2":"Philip McGuire","3":"Kevin McNaughton","4":"Eric Deloumeaux","15":"Kevin Rutkiewicz","11":"Christopher Clark","10":"Laurent D'Jaffo"},"substitutes":{"1":"Ryan Esson","16":"Scott Michie","21":"Stephen Payne","9":"Leon Mike"}},"away":{"formation":"3-5-2","first_11":{"21":"Magnus Hedman","4":"Jackie McNamara","5":"Joos Valgaeren","6":"Bobo Balde","35":"Johan Mjallby","8":"Alan Thompson","14":"Paul Lambert","19":"Stiliyan Petrov","7":"Henrik Larsson","9":"Chris Sutton","10":"John Hartson"},"substitutes":{"1":"Jonathan Gould","40":"Stephen Crainey","39":"Jamie Smith","12":"David Fernandez","29":"Shaun Maloney"}}},"incidents":{"substitutions":[],"yellow cards":[],"red cards":[]}}