{"match":{"goalscorers":{"home":[],"away":["G Dempsey (51)","D Daal (81)"]},"date":"Saturday 16th September 2006","home_team":"Falkirk","away_team":"Aberdeen","ft_home_goals":"0","ft_away_goals":"2","ht_home_goals":"0","ht_away_goals":"0"},"extra_info":{"Attendance":"5,812","Venue":"Falkirk Stadium"},"stats":{"Goals":{"home":"0","away":"2"},"Assists":{"home":"0","away":"2"},"Shots":{"home":"10","away":"10"},"On Target":{"home":"2","away":"3"},"Off Target":{"home":"8","away":"7"},"Corners":{"home":"6","away":"3"},"Fouls":{"home":"12","away":"9"}},"squads":{"home":{"formation":"4-4-2","first_11":[[1,"Scott Higgins"],[5,"John Ross"],[20,"Darren Barr"],[23,"Marc Twaddle"],[27,"Karl Dodd"],[4,"Patrick Cregg"],[8,"Steven Thomson"],[28,"Stephen O'Donnell"],[33,"Thomas Scobbie"],[11,"Anthony Stokes"],[19,"John Stewart"]],"substitutes":[[17,"Jeroen Lambers"],[25,"Tiago Jonas Rodrigues"],[8,"Alan Gow"],[10,"Russell Latapy"],[18,"Vitor Lima"],[26,"Liam Craig"],[7,"Pedro Moutinho"]]},"away":{"formation":"4-4-2","first_11":[[1,"James Langfield"],[2,"Michael Hart"],[4,"Russell Anderson"],[6,"Scott Severin"],[21,"Andrew Considine"],[8,"Barry Nicholson"],[10,"Darren Mackie"],[11,"Christopher Clark"],[14,"Gary Dempsey"],[14,"Richard  Foster"],[16,"Lee Miller"]],"substitutes":[[20,"Derek Soutar"],[17,"Daniel Smith"],[24,"David Donald"],[15,"Jamie Winter"],[22,"Kyle MacAulay"],[22,"Chris Maguire"],[26,"Dyron Daal"]]}},"incidents":{"substitutions":[],"yellow cards":[],"red cards":[]}}