{"match":{"goalscorers":{"home":["J Albertz (38, 57)","N McCann (51, 71)","G Van Bronckhorst (88)"],"away":["D Adamczuk (28)"]},"date":"Saturday 20th February 1999","home_team":"Rangers","away_team":"Dundee","ft_home_goals":"0","ft_away_goals":"0","ht_home_goals":null,"ht_away_goals":null},"extra_info":{"Attendance":"49,462","Venue":"Ibrox Stadium"},"stats":{"Goals":{"home":"0","away":"0"},"On Target":{"home":"0","away":"0"},"Off Target":{"home":"0","away":"0"}},"squads":{"home":{"formation":"","first_11":[[2,"Sergio Porrini"],[4,"Lorenzo Amoruso"],[25,"Tony Vidmar"],[6,"Barry Ferguson"],[8,"Giovanni Van Bronckhorst"],[11,"Jorg Albertz"],[17,"Andrei Kanchelskis"],[20,"Jonatan Johansson"],[1,"Stefan Klos"],[11,"Neil McCann"],[19,"Scott Wilson"]],"substitutes":[[12,"Stephane Guivarc'h"],[13,"Charlie Miller"],[14,"Gabriel Amato"],[15,"Allan McGregor"]]},"away":{"formation":"","first_11":[[1,"Rab Douglas"],[2,"David Rogers"],[3,"Lee Maddison"],[4,"Barry Smith"],[5,"Dariusz Adamczuk"],[6,"Willie Falconer"],[7,"Shaun McSkimming"],[8,"James Grady"],[9,"Tommy Coyne"],[10,"Steve Tweed"],[11,"Gavin Strachan"]],"substitutes":[[12,"James Langfield"],[13,"Lee Sharp"],[14,"Edward Annand"],[15,"Gavin Rae"],[16,"Hugh Robertson"]]}},"incidents":{"substitutions":[],"yellow cards":[],"red cards":[]}}