{"match":{"goalscorers":{"home":["D Goodwillie (7)","J Hayes (pen 87)","R Jack (90+2)"],"away":["G Irvine (38)","G Stewart (40)","G Harkins (48)"]},"date":"Saturday 17th January 2015","home_team":"Aberdeen","away_team":"Dundee","ft_home_goals":"3","ft_away_goals":"3","ht_home_goals":"1","ht_away_goals":"2"},"extra_info":{"Official":"Alan Muir","Attendance":"16,796","Weather":"Clear","Venue":"Pittodrie"},"stats":{"Goals":{"home":"3","away":"3"},"Shots":{"home":"12","away":"4"},"On Target":{"home":"8","away":"0"},"Off Target":{"home":"4","away":"4"},"Corners":{"home":"9","away":"1"},"Saves":{"home":"3","away":"4"},"Free Kicks":{"home":"9","away":"14"},"Yellow Cards":{"home":"0","away":"2"}},"squads":{"home":{"formation":"4-4-1-1","first_11":{"20":"Scott Brown","2":"Shaleum Logan","3":"Andrew Considine","5":"Ashton Taylor","6":"Mark Reynolds","10":"Niall McGinn","11":"Jonathan Hayes","16":"Peter Pawlett","22":"Ryan Jack","9":"Adam Rooney","17":"David Goodwillie"},"substitutes":{"1":"James Langfield","8":"William Flood","14":"Cameron Smith","15":"Barry Robson","21":"Joseph Shaughnessy","23":"Jamie Masson","25":"Lawrence Shankland"}},"away":{"formation":"4-2-3-1","first_11":{"12":"Scott Bain","2":"Gary Irvine","6":"Iain Davidson","19":"Paul McGinn","26":"Kostadin Gadzhalov","10":"Kevin Thomson","15":"Greg Stewart","20":"James McAlister","29":"Gary Harkins","47":"Alexander Harris","21":"Luka Tankulic"},"substitutes":{"3":"William Dyer","4":"Thomas Konrad","11":"Simon Ferry","14":"Philip Roberts","24":"Andrew Black","25":"Arvid Schenk","28":"Dylan Carreiro"}}},"incidents":{"substitutions":{"home":["5. Ashton Taylor (63' injury)","16. Peter Pawlett (63' tactical)","9. Adam Rooney (82' tactical)","8. William Flood (63' injury)","14. Cameron Smith (63' tactical)","25. Lawrence Shankland (82' tactical)"],"away":["26. Kostadin Gadzhalov (88' tactical)","10. Kevin Thomson (90+1' tactical)","21. Luka Tankulic (74' tactical)","3. William Dyer (90+1' tactical)","4. Thomas Konrad (88' tactical)","11. Simon Ferry (74' tactical)"]},"yellow cards":{"away":["6. Iain Davidson  (29', unsporting behaviour)","26. Kostadin Gadzhalov  (44', unsporting behaviour)"]},"red cards":[]}}