{"match":{"goalscorers":{"home":["A Rooney (pen 56)","P Quinn (86)"],"away":["L Griffiths (pen 35)"]},"date":"Saturday 12th September 2015","home_team":"Aberdeen","away_team":"Celtic","ft_home_goals":"2","ft_away_goals":"1","ht_home_goals":"0","ht_away_goals":"1"},"extra_info":{"Official":"Craig Thomson","Attendance":"20,385","Weather":"Clear","Venue":"Pittodrie"},"stats":{"Goals":{"home":"2","away":"1"},"Shots":{"home":"3","away":"12"},"On Target":{"home":"3","away":"10"},"Off Target":{"home":"0","away":"2"},"Corners":{"home":"2","away":"7"},"Saves":{"home":"2","away":"0"},"Free Kicks":{"home":"19","away":"14"},"Yellow Cards":{"home":"1","away":"4"},"Red Cards":{"home":"1","away":"0"}},"squads":{"home":{"formation":"3-5-1-1","first_11":{"19":"Danny Ward","4":"Andrew Considine","5":"Ashton Taylor","18":"Paul Quinn","2":"Shaleum Logan","3":"Graeme Shinnie","10":"Niall McGinn","11":"Jonathan Hayes","22":"Ryan Jack","7":"Kenneth McLean","9":"Adam Rooney"},"substitutes":{"8":"William Flood","15":"Barry Robson","16":"Peter Pawlett","17":"David Goodwillie","20":"Scott Brown","21":"Ryan McLaughlin","32":"Josh Parker"}},"away":{"formation":"4-2-3-1","first_11":{"1":"Craig Gordon","2":"Tyler Blackett","20":"Dedryck Boyata","21":"Charlie Mulgrew","23":"Carl Mikael Lustig","6":"Nir Bitton","8":"Scott Brown","16":"Gary Mackay-Steven","18":"Tomas Rogic","25":"Stefan Johansen","9":"Leigh Griffiths"},"substitutes":{"4":"Efetobore Ambrose Emuobo","7":"Nadir Ciftci","15":"Kristian Commons","22":"Saidy Janko","26":"Logan Bailly","42":"Callum McGregor","49":"James Forrest"}}},"incidents":{"substitutions":{"home":["10. Niall McGinn (87' tactical)","9. Adam Rooney (80' tactical)","8. William Flood (87' tactical)","32. Josh Parker (80' tactical)"],"away":["23. Carl Mikael Lustig (73' tactical)","16. Gary Mackay-Steven (77' tactical)","18. Tomas Rogic (73' tactical)","4. Efetobore Ambrose Emuobo (73' tactical)","7. Nadir Ciftci (77' tactical)","49. James Forrest (73' tactical)"]},"yellow cards":{"home":["4. Andrew Considine  (34', foul)"],"away":["21. Charlie Mulgrew  (40', foul)","23. Carl Mikael Lustig  (70', foul)","25. Stefan Johansen  (61', foul)","4. Efetobore Ambrose Emuobo  (85', foul)"]},"red cards":{"home":["11. Jonathan Hayes  (72', serious foul)"]}}}