{"match":{"goalscorers":{"home":["D Riordan (8)"],"away":["A Rooney (82)"]},"date":"Saturday 11th September 2010","home_team":"Hibernian","away_team":"Inverness CT","ft_home_goals":"1","ft_away_goals":"1","ht_home_goals":"1","ht_away_goals":"0"},"extra_info":{"Official":"Crawford Allan","Attendance":"11,938","Venue":"Easter Road Stadium"},"stats":{"Goals":{"home":"1","away":"1"},"Assists":{"home":"1","away":"0"},"Shots":{"home":"10","away":"10"},"On Target":{"home":"4","away":"2"},"Off Target":{"home":"6","away":"8"},"Corners":{"home":"5","away":"7"},"Fouls":{"home":"11","away":"6"}},"squads":{"home":{"formation":"4-4-2","first_11":[[31,"Mark Brown"],[2,"Michael Hart"],[3,"Jonathan Grounds"],[14,"Francis Dickoh"],[26,"Souleymane Bamba"],[8,"Edwin De Graaf"],[17,"Kevin McBride"],[24,"David Wotherspoon"],[33,"Liam Miller"],[9,"Colin Nish"],[10,"Derek Riordan"]],"substitutes":[[21,"Graeme Smith"],[4,"Chris Hogg"],[6,"Ian Murray"],[15,"Steven Thicot"],[20,"Paul Hanlon"],[11,"John Rankin"],[22,"Daniel Galbraith"]]},"away":{"formation":"4-4-2","first_11":[[1,"Ryan Esson"],[2,"David Proctor"],[3,"Ross Tokely"],[14,"Grant Munro"],[24,"Kenny Gillet"],[4,"Stuart Duff"],[6,"Lee Cox"],[11,"Jonny Hayes"],[7,"Eric Odhiambo"],[10,"Adam Rooney"],[19,"Nick Ross"]],"substitutes":[[12,"Jonny Tuffey"],[15,"Chris Innes"],[16,"Roy McBain"],[8,"Russell Duncan"],[17,"Gavin Morrison"],[20,"Shane Sutherland"],[23,"Dani Sanchez"]]}},"incidents":{"substitutions":[],"yellow cards":[],"red cards":[]}}