{"match":{"goalscorers":{"home":["A Sodje (66)"],"away":["J Chambers (9)"," L Miller (34)"]},"date":"Sunday 17th April 2011","home_team":"Hibernian","away_team":"Hamilton Accies","ft_home_goals":"1","ft_away_goals":"2","ht_home_goals":"0","ht_away_goals":"2"},"extra_info":{"Official":"Brian Winter","Attendance":"8,173","Venue":"Easter Road Stadium"},"stats":{"Goals":{"home":"1","away":"2"},"Assists":{"home":"1","away":"1"},"Shots":{"home":"24","away":"6"},"On Target":{"home":"15","away":"1"},"Off Target":{"home":"9","away":"5"},"Corners":{"home":"16","away":"2"},"Fouls":{"home":"8","away":"8"}},"squads":{"home":{"formation":"4-4-2","first_11":[[31,"Mark Brown"],[14,"Francis Dickoh"],[20,"Paul Hanlon"],[28,"Callum Booth"],[34,"Richie Towell"],[24,"David Wotherspoon"],[33,"Liam Miller"],[91,"Victor Palsson"],[8,"Ricardo Vaz Te"],[10,"Derek Riordan"],[18,"Akpo Sodje"]],"substitutes":[[41,"Jakub Divis"],[6,"Ian Murray"],[25,"David Stephens"],[16,"Lewis Stevenson"],[44,"Martin Scott"],[9,"Colin Nish"],[19,"Darryl Duffy"]]},"away":{"formation":"4-5-1","first_11":[[19,"Sean Murdoch"],[12,"David Buchanan"],[33,"Lee Kilday"],[8,"Gary McDonald"],[11,"James McAlister"],[16,"James Chambers"],[17,"Alister Crawford"],[27,"Simon Mensing"],[7,"Dougie Imrie"],[10,"Alexander Neil"],[30,"Nigel Hasselbaink"]],"substitutes":[[1,"Tomas Cerny"],[5,"Andrew Graham"],[3,"Gavin Skelton"],[13,"Mark Carrington"],[24,"Grant Gillespie"],[28,"David Hopkirk"],[36,"Tom Elliott"]]}},"incidents":{"substitutions":[],"yellow cards":[],"red cards":[]}}