{"match":{"goalscorers":{"home":["S Tosh (26)"],"away":[]},"date":"Saturday 27th November 2004","home_team":"Aberdeen","away_team":"Dundee United","ft_home_goals":"1","ft_away_goals":"0","ht_home_goals":"1","ht_away_goals":"0"},"extra_info":{"Attendance":"12,038","Venue":"Pittodrie Stadium"},"stats":{"Goals":{"home":"1","away":"0"},"Assists":{"home":"1","away":"0"},"Shots":{"home":"4","away":"6"},"On Target":{"home":"2","away":"3"},"Off Target":{"home":"2","away":"3"},"Corners":{"home":"5","away":"6"},"Fouls":{"home":"11","away":"11"}},"squads":{"home":{"formation":"4-4-2","first_11":{"30":"David Preece","2":"Philip McGuire","3":"Kevin McNaughton","5":"Zander Diamond","8":"Markus Heikkinen","14":"Richard  Foster","7":"Steven Tosh","16":"Scott Morrison","6":"Scott Severin","10":"Darren Mackie","23":"Noel Whelan"},"substitutes":{"18":"Scott Muirhead","24":"Fernando Pasquinelli","25":"Steven Craig","26":"Ryan O'Leary","1":"Ryan Esson","16":"John Stewart"}},"away":{"formation":"4-4-2","first_11":{"24":"Stuart Duff","3":"David McCracken","6":"Alan Archibald","23":"Paul Ritchie","2":"Mark Wilson","4":"Derek McInnes","8":"Grant Brebner","11":"Barry Robson","10":"Jim McIntyre","16":"James Grady"},"substitutes":{"17":"Greg Cameron","19":"Ross Gardiner","25":"Chris Innes","21":"Karim Kerkar","20":"Jason Scotland"}}},"incidents":{"substitutions":[],"yellow cards":[],"red cards":[]}}