{"match":{"goalscorers":{"home":["F Zhiyi (66)"],"away":[]},"date":"Saturday 12th January 2002","home_team":"Dundee","away_team":"Hibernian","ft_home_goals":"1","ft_away_goals":"0","ht_home_goals":"0","ht_away_goals":"0"},"extra_info":{"Attendance":"7,326","Venue":"Dens Park Stadium"},"stats":{"Goals":{"home":"1","away":"0"},"Assists":{"home":"1","away":"0"},"Shots":{"home":"9","away":"11"},"On Target":{"home":"4","away":"4"},"Off Target":{"home":"5","away":"7"},"Corners":{"home":"5","away":"7"},"Fouls":{"home":"13","away":"18"},"Red Cards":{"home":"0","away":"1"}},"squads":{"home":{"formation":"4-4-2","first_11":[[1,"Julian Speroni"],[6,"Barry Smith"],[17,"Walter Del Rio"],[25,"Gavin Beith"],[30,"Massimo Beghetto"],[31,"Fan Zhiyi"],[6,"Temuri Ketsbaia"],[18,"Javier Artero"],[21,"Alessandro Romano"],[7,"Fabian Caballero"],[15,"Steven Milne"]],"substitutes":[[12,"James Langfield"],[3,"David Mackay"],[14,"Beto Garrido"],[9,"Juan Sara"],[28,"Khaled Khemas"]]},"away":{"formation":"4-4-2","first_11":[[1,"Nick Colgan"],[2,"Ulises De la Cruz"],[3,"Ulrik Laursen"],[5,"Gary Smith"],[6,"Ian Murray"],[25,"Paul Fenwick"],[8,"Grant Brebner"],[8,"Frederic Arpinon"],[11,"John O'Neill"],[7,"Tom McManus"],[7,"Garry O'Connor"]],"substitutes":[[30,"Tony Caig"],[19,"Matthias Jack"],[12,"Derek Townsley"],[7,"Francisco Luna"],[20,"David Zitelli"]]}},"incidents":{"substitutions":[],"yellow cards":[],"red cards":[]}}