{"match":{"goalscorers":{"home":["J Vincent (pen 48)","A Doran Cogan (49)","B McKay (59)"],"away":[]},"date":"Saturday 3rd August 2013","home_team":"Inverness CT","away_team":"St Mirren","ft_home_goals":"3","ft_away_goals":"0","ht_home_goals":"0","ht_away_goals":"0"},"extra_info":{"Official":"Kevin Clancy","Attendance":"3,215","Weather":"Windy","Venue":"Tulloch Caledonian Stadium"},"stats":{"Goals":{"home":"3","away":"0"},"Shots":{"home":"12","away":"7"},"On Target":{"home":"7","away":"5"},"Off Target":{"home":"5","away":"2"},"Saves":{"home":"2","away":"5"},"Blocks":{"home":"0","away":"1"},"Free Kicks":{"home":"14","away":"17"},"Fouls":{"home":"16","away":"12"},"Yellow Cards":{"home":"3","away":"4"},"Red Cards":{"home":"0","away":"1"}},"squads":{"home":{"formation":"4-4-1-1","first_11":[[12,"Dean Brill"],[2,"David Raven"],[3,"Graeme Shinnie"],[5,"Gary Warren"],[6,"Josh Meekings"],[8,"Ross Draper"],[9,"Richie Foran"],[10,"Aaron Doran Cogan"],[11,"Nicholas Ross"],[4,"James Vincent"],[7,"Billy McKay"]],"substitutes":[[1,"Ryan Esson"],[14,"Danny Devine"],[17,"Ben Greenhalgh"],[18,"Carl Tremarco"],[19,"Danny Williams"],[20,"Liam Polworth"],[23,"Torbjorn Agdestein"]]},"away":{"formation":"4-2-3-1","first_11":[[1,"David Cornell"],[2,"David van Zanten"],[6,"James Goodwin"],[14,"Marc McAusland"],[27,"Danny Grainger"],[7,"John McGinn"],[8,"Gary Harkins"],[10,"Paul McGowan"],[17,"Thomas Reilly"],[21,"Gary Teale"],[9,"Steven Thompson"]],"substitutes":[[4,"Darren McGregor"],[15,"Jon Robertson"],[18,"Sean Kelly"],[20,"Kealan Dillon"],[22,"Jason Naismith"],[26,"Anthony Brady"],[30,"Christopher Dilo"]]}},"incidents":{"substitutions":{"home":["8. Ross Draper (81' tactical)","10. Aaron Doran Cogan (89' tactical)","4. James Vincent (83' tactical)","19. Danny Williams (89' tactical)","20. Liam Polworth (81' tactical)","23. Torbjorn Agdestein (83' tactical)"],"away":["7. John McGinn (65' tactical)","10. Paul McGowan (65' tactical)","15. Jon Robertson (65' tactical)","18. Sean Kelly (65' tactical)"]},"yellow cards":{"home":["2. David Raven  (82', unsporting behaviour)","5. Gary Warren  (39', unsporting behaviour)","8. Ross Draper  (62', unsporting behaviour)"],"away":["2. David van Zanten  (46', unsporting behaviour)","7. John McGinn  (41', unsporting behaviour)","10. Paul McGowan  (45', unsporting behaviour)","9. Steven Thompson  (28', unsporting behaviour)"]},"red cards":[]}}