{"match":{"goalscorers":{"home":["R Draper (16)","G Tansey (34)"],"away":["J Naismith (3)","S Kelly (62)"]},"date":"Saturday 29th March 2014","home_team":"Inverness CT","away_team":"St Mirren","ft_home_goals":"2","ft_away_goals":"2","ht_home_goals":"2","ht_away_goals":"1"},"extra_info":{"Official":"William Collum","Attendance":"3,032","Weather":"Clear","Venue":"Tulloch Caledonian Stadium"},"stats":{"Goals":{"home":"2","away":"2"},"Shots":{"home":"5","away":"8"},"On Target":{"home":"3","away":"7"},"Off Target":{"home":"2","away":"1"},"Corners":{"home":"6","away":"6"},"Saves":{"home":"1","away":"2"},"Blocks":{"home":"3","away":"1"},"Free Kicks":{"home":"15","away":"16"},"Yellow Cards":{"home":"0","away":"1"},"Red Cards":{"home":"1","away":"0"}},"squads":{"home":{"formation":"4-4-1-1","first_11":{"12":"Dean Brill","2":"David Raven","3":"Graeme Shinnie","5":"Gary Warren","6":"Josh Meekings","4":"James Vincent","8":"Ross Draper","16":"Greg Tansey","20":"Liam Polworth","7":"Billy McKay","36":"Ryan Christie"},"substitutes":{"1":"Ryan Esson","11":"Nicholas Ross","14":"Danny Devine","15":"Marley Watkins","18":"Carl Tremarco","19":"Danny Williams","40":"Adam Evans"}},"away":{"formation":"4-3-3","first_11":{"30":"Christopher Dilo","4":"Darren McGregor","6":"James Goodwin","18":"Sean Kelly","22":"Jason Naismith","7":"John McGinn","11":"Kenneth McLean","24":"Conor Newton","9":"Steven Thompson","12":"Adam Campbell","39":"Gregg Wylde"},"substitutes":{"2":"David van Zanten","14":"Marc McAusland","16":"Josh Magennis","17":"Thomas Reilly","21":"Gary Teale","40":"Paul Mathers","99":"Eric Djemba-Djemba"}}},"incidents":{"substitutions":{"home":["16. Greg Tansey (51' injury)","7. Billy McKay (72' tactical)","36. Ryan Christie (69' tactical)","11. Nicholas Ross (51' injury)","14. Danny Devine (69' tactical)","15. Marley Watkins (72' tactical)"],"away":["7. John McGinn (50' tactical)","12. Adam Campbell (64' tactical)","39. Gregg Wylde (64' tactical)","14. Marc McAusland (50' tactical)","16. Josh Magennis (64' tactical)","21. Gary Teale (64' tactical)"]},"yellow cards":{"away":["14. Marc McAusland  (73', unsporting behaviour)"]},"red cards":{"home":["6. Josh Meekings  (68', denied goal-scoring opportunity)"]}}}