{"match":{"goalscorers":[],"date":"Saturday 28th September 2013","home_team":"Hearts","away_team":"Dundee United","ft_home_goals":"0","ft_away_goals":"0","ht_home_goals":"0","ht_away_goals":"0"},"extra_info":{"Official":"Steven McLean","Attendance":"13,970","Weather":"Sunny","Venue":"Tynecastle"},"stats":{"Goals":{"home":"0","away":"0"},"Shots":{"home":"11","away":"12"},"On Target":{"home":"6","away":"8"},"Off Target":{"home":"5","away":"4"},"Corners":{"home":"6","away":"5"},"Saves":{"home":"4","away":"5"},"Free Kicks":{"home":"15","away":"10"},"Yellow Cards":{"home":"0","away":"1"}},"squads":{"home":{"formation":"4-5-1","first_11":[[1,"Jamie MacDonald"],[3,"Kevin McHattie"],[4,"Danny Wilson"],[5,"Dylan McGowan"],[30,"Jordan McGhee"],[2,"Jamie Hamill"],[8,"Scott Robinson"],[12,"Callum Paterson"],[14,"Jamie Walker"],[15,"Jason Holt"],[17,"David Smith"]],"substitutes":[[7,"Ryan Stevenson"],[13,"Mark Ridgers"],[16,"Brad McKay"],[18,"Dale Carrick"],[19,"Billy King"],[20,"Callum Tapping"],[29,"Gary Oliver"]]},"away":{"formation":"4-4-2","first_11":[[1,"Radoslaw Cierzniak"],[2,"Sean Dillon"],[6,"Paul Paton"],[12,"Keith Watson"],[26,"Andrew Robertson"],[8,"John Rankin"],[10,"Stuart Armstrong"],[19,"Ryan Gauld"],[20,"John Souttar"],[7,"David Goodwillie"],[21,"Nadir Ciftci"]],"substitutes":[[4,"Calum Butcher"],[9,"Brian Graham"],[11,"Gary Mackay-Steven"],[16,"Mark Wilson"],[18,"Ryan Dow"],[25,"Marc McCallum"],[40,"Darren Petrie"]]}},"incidents":{"substitutions":{"home":["8. Scott Robinson (45' injury)","15. Jason Holt (71' tactical)","17. David Smith (64' tactical)","7. Ryan Stevenson (71' tactical)","19. Billy King (64' tactical)","20. Callum Tapping (45' injury)"],"away":["19. Ryan Gauld (67' tactical)","11. Gary Mackay-Steven (67' tactical)"]},"yellow cards":{"away":["21. Nadir Ciftci  (90', persistent infringement)"]},"red cards":[]}}