{"match":{"goalscorers":{"home":["S Stanton (88)"],"away":["K Doolan (8)"]},"date":"Saturday 3rd May 2014","home_team":"Hibernian","away_team":"Partick Thistle","ft_home_goals":"1","ft_away_goals":"1","ht_home_goals":"0","ht_away_goals":"1"},"extra_info":{"Official":"Alan Muir","Attendance":"10,740","Weather":"Clear","Venue":"Easter Road"},"stats":{"Goals":{"home":"1","away":"1"},"Shots":{"home":"10","away":"9"},"On Target":{"home":"7","away":"4"},"Off Target":{"home":"3","away":"5"},"Corners":{"home":"7","away":"9"},"Saves":{"home":"5","away":"3"},"Free Kicks":{"home":"10","away":"12"},"Yellow Cards":{"home":"2","away":"1"},"Red Cards":{"home":"1","away":"0"}},"squads":{"home":{"formation":"4-4-2","first_11":[[1,"Ben Williams"],[3,"Ryan McGivern"],[5,"Michael Nelson"],[16,"Lewis Stevenson"],[18,"Alan Maybury"],[8,"Scott Robertson"],[10,"Liam Craig"],[35,"Jason Cummings"],[38,"Kevin Thomson"],[7,"Alexander Harris"],[26,"Samuel Stanton"]],"substitutes":[[6,"James McPake"],[11,"Paul Cairney"],[14,"James Collins"],[17,"Owain Tudur-Jones"],[19,"Daniel Handling"],[21,"Sean Murdoch"],[22,"Duncan Watmore"]]},"away":{"formation":"4-4-2","first_11":[[12,"Paul Gallacher"],[3,"Aaron Taylor-Sinclair"],[6,"Conrad Balatoni"],[15,"Lee Mair"],[16,"Jordan McMillan"],[8,"Stuart Bannigan"],[22,"Gary Fraser"],[23,"Kallum Higginbotham"],[28,"Christopher Erskine"],[7,"James Craigen"],[9,"Kris Doolan"]],"substitutes":[[1,"Scott Fox"],[11,"Steven Lawless"],[13,"Gabriel Rojo de la Vega Piccolo"],[14,"Christie Elliott"],[17,"George Moncur"],[21,"Lyle Taylor"],[30,"Dale Keenan"]]}},"incidents":{"substitutions":{"home":["8. Scott Robertson (84' tactical)","38. Kevin Thomson (46' injury)","7. Alexander Harris (62' tactical)","14. James Collins (46' injury)","19. Daniel Handling (84' tactical)","22. Duncan Watmore (62' tactical)"],"away":["15. Lee Mair (45' injury)","28. Christopher Erskine (74' tactical)","9. Kris Doolan (19' injury)","13. Gabriel Rojo de la Vega Piccolo (45' injury)","14. Christie Elliott (74' tactical)","21. Lyle Taylor (19' injury)"]},"yellow cards":{"home":["5. Michael Nelson  (58', unsporting behaviour)","26. Samuel Stanton  (89', unsporting behaviour)"],"away":["28. Christopher Erskine  (70', unsporting behaviour)"]},"red cards":[]}}