{"match":{"goalscorers":{"home":[],"away":["L Craig (38)"]},"date":"Saturday 4th May 2013","home_team":"Dundee United","away_team":"St Johnstone","ft_home_goals":"0","ft_away_goals":"1","ht_home_goals":"0","ht_away_goals":"1"},"extra_info":{"Official":"Euan Norris","Attendance":"6,437","Venue":"Tannadice Park"},"stats":{"Goals":{"home":"0","away":"1"},"Assists":{"home":"0","away":"1"},"Shots":{"home":"3","away":"5"},"On Target":{"home":"1","away":"4"},"Off Target":{"home":"2","away":"1"},"Corners":{"home":"3","away":"6"},"Fouls":{"home":"8","away":"5"}},"squads":{"home":{"formation":"4-4-1-1","first_11":{"1":"Radoslaw Cierzniak","2":"Sean Dillon","4":"Brian McLean","33":"Luke Johnston","44":"John Souttar","6":"William Flood","11":"Gary Mackay-Steven","14":"Mark Millar","16":"Stuart Armstrong","9":"Jon Daly","15":"Michael Gardyne"},"substitutes":{"31":"Philip Anderson","8":"John Rankin","38":"Ryan Gauld","45":"Euan Spark","7":"Johnny Russell","18":"Ryan Dow","19":"Rory Boulding"}},"away":{"formation":"4-3-3","first_11":{"1":"Alan Mannus","2":"David Mackay","5":"Frazer Wright","6":"Steven Anderson","33":"Thomas Scobbie","7":"Christopher Millar","8":"Murray Davidson","10":"Liam Craig","9":"Gregory Tade","17":"Steven MacLean","23":"Rowan Vine"},"substitutes":{"15":"Jonny Tuffey","19":"Gary Miller","26":"Liam Caddis","4":"Patrick Cregg","14":"Gwion  Edwards","16":"Michael Doughty","11":"Nigel Hasselbaink"}}},"incidents":{"substitutions":[],"yellow cards":[],"red cards":[]}}