{"match":{"goalscorers":{"home":["R Brittain (59)","D Mackay (77)"],"away":["B Aguiar (17)","E Jankauskas (72)","R Bednar (87)"]},"date":"Sunday 5th March 2006","home_team":"Livingston","away_team":"Hearts","ft_home_goals":"2","ft_away_goals":"3","ht_home_goals":"0","ht_away_goals":"1"},"extra_info":{"Attendance":"5,058","Venue":"Almondvale Stadium"},"stats":{"Goals":{"home":"2","away":"3"},"Assists":{"home":"0","away":"2"},"Shots":{"home":"9","away":"13"},"On Target":{"home":"4","away":"7"},"Off Target":{"home":"5","away":"6"},"Corners":{"home":"3","away":"7"},"Fouls":{"home":"16","away":"14"}},"squads":{"home":{"formation":"4-4-2","first_11":{"1":"Roderick McKenzie","2":"David McNamee","5":"Greg Strong","6":"David Mackay","8":"Allan Walker","11":"Jason Dair","7":"Richard Brittain","9":"Sam Morrow"},"substitutes":{"17":"Ludovic Roy","10":"Robert Snodgrass","27":"Steven Weir"}},"away":{"formation":"4-4-2","first_11":{"1":"Craig Gordon","2":"Robbie Neilson","3":"Panagiotis Fyssas","4":"Andy Webster","18":"Deividas Cesnauskis","8":"Rudi Skacel","9":"Edgaras Jankauskas","22":"Calum Elliot"},"substitutes":{"13":"Steve Banks","6":"Jose Goncalves","25":"Jamie McAllister","14":"Mirsad Beslija","24":"Lee Johnson","26":"Chris Hackett","12":"Roman Bednar"}}},"incidents":{"substitutions":[],"yellow cards":[],"red cards":[]}}